Workbook

Sheet README
B2: Nuclear Project Deployment Incentives on Tribal Lands — Scenario Analysis
B4: VERSION: v2 (May 2026) — incorporates updates from sanity-check comparison report.
B6: Purpose:
B7: This workbook models three illustrative nuclear project scenarios on Tribal lands and shows the financial impact
B8: of stacking the available federal incentives (Section 48E ITC, bonus adders, Direct Pay, and DOE loan support).
B10: Scenarios included:
B11: • Scenario A — Microreactor (3 MW) on Tribal land — qualifies for the §48E(h) Indian Land bonus + LIC stack.
B12: • Scenario B — Small Modular Reactor (300 MW) on Tribal land — base ITC + domestic content + energy community.
B13: • Scenario C — Advanced Reactor (1,000 MW / large) on Tribal land near a former coal site — full energy community stack.
B15: Sheets:
B16: • README — this overview.
B17: • Assumptions — every input cell has a comment with the source URL.
... B50: Date prepared: May 2026 — reflects post-OBBBA (One Big Beautiful Bill Act, signed July 4, 2025) law.

Sheet Assumptions
B2: Project Assumptions — Three Scenarios
B4: Parameter | C4: Scenario A: Microreactor | D4: Scenario B: SMR | E4: Scenario C: Large Reactor | F4: Source / Notes
B5: PROJECT BASICS
B6: Reactor type | C6: Microreactor | D6: Small Modular Reactor (SMR) | E6: Large advanced reactor | F6: Examples: A=Westinghouse eVinci (5 MWe), Oklo Aurora (~1.5 MWe). B=NuScale VOYGR (77 MWe/module), GE-Hitachi BWRX-300. C=AP1000-class.
B7: Net electrical output (MWe) | C7: 3 | D7: 300 | E7: 1000 | F7: Microreactor: 1–10 MWe range per IAEA. SMR: up to 300 MWe per IAEA. Large: ~1,000 MWe (e.g., AP1000 = 1,117 MWe).
B8: Overnight capital cost ($/kW) | C8: 20000 | D8: 7500 | E8: 6500 | F8: FOAK microreactors estimated $15–25k/kW (Idaho Nat'l Lab studies). SMR FOAK $7–10k/kW (NIA Dec 2023 report). Large FOAK $6–8k/kW (NIA modeling).
B9: Total project cost ($) | C9: =C7*C8*1000 -> 60000000 | D9: =D7*D8*1000 -> 2250000000 | E9: =E7*E8*1000 -> 6500000000 | F9: Calculated: MWe × $/kW × 1,000. Represents qualified investment cost basis for §48E ITC purposes.
B11: ELIGIBILITY & SITE CHARACTERISTICS
B12: Located on Tribal land? | C12: Yes | D12: Yes | E12: Yes | F12: All three scenarios assumed on federally recognized Tribal land per 25 U.S.C. §3501(2).
B13: Net output <5 MW (qualifies §48E(h))? | C13: Yes | D13: No | E13: No | F13: §48E(h) Indian Land bonus is statutorily limited to facilities <5 MW net output. SMRs (300 MW) and large reactors do not qualify.
B14: In Energy Community (brownfield/coal/fossil)? | C14: No | D14: Yes (former coal area) | E14: Yes (brownfield + coal MSA) | F14: Scenario B sited in former coal-fired plant census tract; Scenario C on a brownfield within a coal MSA. Scenario A on greenfield Tribal land.
B15: Domestic content compliant? | C15: Yes | D15: Yes | E15: Yes | F15: Assumed: 100% US steel/iron + ≥40% (rising to 55%) US-manufactured product cost share, per CRS R48358.
B16: PWA (prevailing wage & apprenticeship) met? | C16: Yes | D16: Yes | E16: Yes | F16: Required to access 30% base ITC vs. 6% un-bonused. All major nuclear projects assumed to comply.
B17: Tribe takes Direct Pay (§6417)? | C17: Yes | D17: Yes | E17: Yes | F17: Tribal governments are tax-exempt and elect to receive credits as cash refund from IRS. Pre-registration via IRS Energy Credits Online required.
B18: Begin construction year | C18: 2027 | D18: 2030 | E18: 2032 | F18: All assumed pre-2034, so full 100% credit value applies (no OBBBA phasedown haircut).
B20: APPLICABLE CREDIT RATES
B21: §48E base ITC rate (with PWA) | C21: 0.3 | D21: 0.3 | E21: 0.3 | F21: 30% with PWA met. Without PWA, the rate would be 6%. This is the technology-neutral Clean Electricity ITC.
B22: Domestic content adder | C22: 0.1 | D22: 0.1 | E22: 0.1 | F22: +10 percentage points if 100% US steel/iron and qualifying % of US-manufactured products. Applies to nuclear of any size.
B23: Energy community adder | C23: 0 | D23: 0.1 | E23: 0.1 | F23: +10 pp if site is brownfield, coal closure tract, or fossil-fuel statistical area. Scenario A is greenfield, so no adder.
B24: §48E(h) Indian Land adder (microreactor only) | C24: 0.1 | D24: 0 | E24: 0 | F24: +10 pp under §48E(h) Cat. 2 (Indian Land). Limited to facilities <5 MW. Requires DOE/IRS allocation in 2026 program window.
B25: §48E(h) Low-Income Economic Benefit adder (Cat. 4) | C25: 0 | D25: 0 | E25: 0 | F25: +20 pp if ≥50% of electricity benefits flow to low-income households. Not assumed here, but available to microreactors with such commitments.
B26: Total ITC % (capped at 70%) | C26: =MIN(0.7,SUM(C21:C25)) -> 0.5 | D26: =MIN(0.7,SUM(D21:D25)) -> 0.5 | E26: =MIN(0.7,SUM(E21:E25)) -> 0.5 | F26: Sum of base + adders, with 70% statutory ceiling on §48(e)/§48E(h) stack.
B28: DOE FINANCING (illustrative)
B29: DOE TEFP loan guarantee % of project cost | C29: 0.5 | D29: 0.8 | E29: 0.8 | F29: TEFP under Title XXVI EPAct 1992 (as amended). Up to $20B in loan guarantee authority. STATUTORY CEILING: TEFP can support up to 80% of eligible project costs per DOE FAQ. Scenario A modeled at 50% (smaller, simpler microreactor); Scenarios B and C at the 80% cap.
B30: Cost of debt savings vs. commercial (bps) | C30: 200 | D30: 200 | E30: 200 | F30: TEFP loan guarantees lower the cost of debt by an estimated 100–300 bps vs. commercial debt (industry estimate). Mid-range 200 bps used here.
B31: DOE Office of Indian Energy grant ($) | C31: 1500000 | D31: 2500000 | E31: 2500000 | F31: Updated to current $50M NOFO 'Unleashing Tribal Energy Development' (DE-FOA-0003548, deadline July 24, 2026). TA1 (community construction, up to $7.5M, 10% cost share); TA2 (community pre-development, up to $1.5M); TA3 (large-scale planning/feasibility, up to $2.5M). Scenarios B and C use TA3 cap; Scenario A uses TA2 cap (community-scale microreactor).

Sheet Scenario Model
B2: Scenario Model — Incentive Stack & Net Project Cost
B4: Line Item | C4: Scenario A: Microreactor | D4: Scenario B: SMR | E4: Scenario C: Large Reactor | F4: Calculation Notes
B5: PROJECT COST
B6: Net output (MW) | C6: =Assumptions!C7 -> 3 | D6: =Assumptions!D7 -> 300 | E6: =Assumptions!E7 -> 1000 | F6: From Assumptions tab (row 7).
B7: Overnight capital cost ($/kW) | C7: =Assumptions!C8 -> 20000 | D7: =Assumptions!D8 -> 7500 | E7: =Assumptions!E8 -> 6500 | F7: From Assumptions tab (row 8).
B8: Total project cost ($) | C8: =C6*C7*1000 -> 60000000 | D8: =D6*D7*1000 -> 2250000000 | E8: =E6*E7*1000 -> 6500000000 | F8: MW × $/kW × 1,000. Equals qualified cost basis for §48E ITC.
B10: §48E ITC STACK
B11: Base ITC % (with PWA) | C11: =Assumptions!C21 -> 0.3 | D11: =Assumptions!D21 -> 0.3 | E11: =Assumptions!E21 -> 0.3 | F11: 30% if PWA met, else 6%. From Assumptions row 21.
B12: Domestic content adder % | C12: =Assumptions!C22 -> 0.1 | D12: =Assumptions!D22 -> 0.1 | E12: =Assumptions!E22 -> 0.1 | F12: +10 pp if 100% US steel/iron + qualifying US-manufactured product %. From Assumptions row 22.
B13: Energy community adder % | C13: =Assumptions!C23 -> 0 | D13: =Assumptions!D23 -> 0.1 | E13: =Assumptions!E23 -> 0.1 | F13: +10 pp if site qualifies as energy community. From Assumptions row 23.
B14: §48E(h) Indian Land adder % (Cat. 2) | C14: =Assumptions!C24 -> 0.1 | D14: =Assumptions!D24 -> 0 | E14: =Assumptions!E24 -> 0 | F14: +10 pp under §48E(h) — only for facilities <5 MW. From Assumptions row 24.
B15: §48E(h) Low-Income Economic Benefit adder % (Cat. 4) | C15: =Assumptions!C25 -> 0 | D15: =Assumptions!D25 -> 0 | E15: =Assumptions!E25 -> 0 | F15: +20 pp if ≥50% of benefits flow to low-income households. From Assumptions row 25.
B16: Total ITC % (capped at 70%) | C16: =MIN(0.7, SUM(C11:C15)) -> 0.5 | D16: =MIN(0.7, SUM(D11:D15)) -> 0.5 | E16: =MIN(0.7, SUM(E11:E15)) -> 0.5 | F16: Sum of all adders, statutory cap 70%.
B17: ITC dollar value (= Direct Pay refund) | C17: =C8*C16 -> 30000000 | D17: =D8*D16 -> 1125000000 | E17: =E8*E16 -> 3250000000 | F17: For Tribes electing §6417 Direct Pay, this becomes a cash refund from IRS.
B19: DOE NON-TAX FINANCING
B20: DOE TEFP loan guarantee coverage % | C20: =Assumptions!C29 -> 0.5 | D20: =Assumptions!D29 -> 0.8 | E20: =Assumptions!E29 -> 0.8 | F20: % of project cost covered by DOE Tribal Energy Financing Program loan guarantee. From Assumptions row 29.
B21: DOE TEFP loan guarantee amount ($) | C21: =C8*C20 -> 30000000 | D21: =D8*D20 -> 1800000000 | E21: =E8*E20 -> 5200000000 | F21: Project cost × coverage %. Up to $20B in TEFP guarantee authority.
B22: DOE Office of Indian Energy grant ($) | C22: =Assumptions!C31 -> 1500000 | D22: =Assumptions!D31 -> 2500000 | E22: =Assumptions!E31 -> 2500000 | F22: Capacity-building / planning grant. From DOE-IE NOFO ($100k–$5M range). From Assumptions row 31.
B23: Estimated debt cost savings (pv, $) | C23: =C21*Assumptions!C30/10000*15 -> 9000000 | D23: =D21*Assumptions!D30/10000*15 -> 540000000 | E23: =E21*Assumptions!E30/10000*15 -> 1560000000 | F23: Illustrative: TEFP-guaranteed debt amount × bps savings/10,000 × 15-year tenor (simplified, undiscounted).
B25: NET FEDERAL SUPPORT TO PROJECT
B26: Direct cash benefit (ITC + grants + debt savings) | C26: =C17+C22+C23 -> 40500000 | D26: =D17+D22+D23 -> 1667500000 | E26: =E17+E22+E23 -> 4812500000 | F26: Sum of all direct dollar-value federal benefits captured in this model.
B27: Net effective project cost after federal support | C27: =C8-C26 -> 19500000 | D27: =D8-D26 -> 582500000 | E27: =E8-E26 -> 1687500000 | F27: Project cost minus total federal benefits. Excludes loan-guarantee leverage effects.
B28: % federal support of total project cost | C28: =C26/C8 -> 0.675 | D28: =D26/D8 -> 0.74111111 | E28: =E26/E8 -> 0.74038462 | F28: Combined federal support as % of overnight capital cost.
B30: APPLICATION & TIMING REQUIREMENTS
B31: §48E ITC + Direct Pay registration | C31: Required (IRS ECO portal) | D31: Required (IRS ECO portal) | E31: Required (IRS ECO portal) | F31: Pre-filing registration before placed-in-service. No competitive component.
B32: §48E(h) Indian Land bonus application | C32: Required — 2026 window: Feb 2 – Aug 7, 2026 | D32: N/A (>5 MW) | E32: N/A (>5 MW) | F32: Competitive allocation. 200 MW carve-out for Indian Land Cat. 2 in 2026.
B33: Domestic content documentation | C33: Required | D33: Required | E33: Required | F33: Supplier certifications + cost analysis. Mandatory for Direct Pay starting BOC 2026.
B34: Energy community substantiation | C34: N/A | D34: Required | E34: Required | F34: Brownfield assessment, MSA employment data, or coal-closure tract evidence.
B35: DOE TEFP loan guarantee | C35: Optional | D35: Recommended | E35: Recommended | F35: LPO Part I/Part II application. Multi-year process (per GAO-25-108720).
B36: DOE-IE grant (capacity / planning) | C36: Recommended | D36: Recommended | E36: Optional | F36: NOFO via IE-Exchange. ~90 days to submit after NOFO release. 50% cost share typical.
B37: Begin-construction deadline (full credit) | C37: Before 2034 | D37: Before 2034 | E37: Before 2034 | F37: Post-OBBBA: 100% credit through 2033; 75% in 2034; 50% in 2035; 0% in 2036+.

Sheet Methodology Notes
B2: Methodology Notes — Important Caveats and Refinements
B4: Topic | C4: Note
B5: ITC vs PTC adder math | C5: CRITICAL DISTINCTION. The bonus adders (domestic content, energy community, Indian land, low-income economic benefit) work DIFFERENTLY for the ITC vs PTC: • ITC adders are ADDITIVE percentage points on cost basis (e.g., 30% + 10% + 10% = 50% of cost basis). • PTC adders are MULTIPLICATIVE on the credit rate (e.g., $30/MWh × 1.10 × 1.10 = $36.30/MWh). This makes the ITC stack slightly more generous than the PTC stack when multiple adders apply. Source: IRS Notice 2023-29; IRS Notice 2023-38; Morgan Lewis confirms domestic content adder is '10% (not 10 percentage points)' for the PTC. This model uses the ITC throughout.
B6: Energy Community pre-qualification | C6: Many Tribal lands automatically qualify for the +10 pp Energy Community adder due to historical uranium and fossil fuel activity. From 1950–1980, 96% of all U.S. defense-related uranium mines were on Tribal land (Navajo, Pueblo of Laguna, Pueblo of Zuni, Hualapai, Tohono O'odham, Spokane, Ute). Many of these former mining areas qualify as brownfield sites under CERCLA. Project developers should check site eligibility at the DOE/NETL Energy Community Mapping Tool: https://arcgis.netl.doe.gov/portal/apps/experiencebuilder/experience/?id=785ee47a99d24b36b405acd03d97a5f9 Tribal lands hosting closed coal plants or in fossil-fuel statistical areas may also qualify. Source: Wilson Center, Nuclear Power is Tribal Power.
B7: §48E(h) Indian Land bonus 5 MW cap | C7: The +10 pp Indian Land bonus applies ONLY to facilities with maximum net output under 5 MW. Microreactors (typically 1–10 MWe) may qualify; SMRs (50–300 MWe) and large reactors do NOT. This is a frequent point of confusion. Source: IRC §48E(h)(2)(A); IRS Rev. Proc. 2025-11.
B8: PWA <1 MW exemption | C8: Facilities with maximum net output under 1 MW are statutorily exempt from prevailing wage and apprenticeship requirements and automatically receive the full 30% ITC base rate. Most realistic Tribal microreactor projects (3–5 MWe) do NOT qualify for this exemption. Source: IRC §48E(a)(2)(A); Plante Moran 2025.
B9: Direct Pay vs Transferability | C9: Tribal governments using §6417 Direct Pay receive 100% of credit value as a tax refund. Private developers using §6418 Transferability typically sell credits at 92–94 cents on the dollar (per Crux Climate market data 2024–2025). On a $1.1B SMR ITC, the Direct Pay advantage to the Tribe is ~$66–88M of preserved value vs. selling the credits.
B10: TEFP loan ceiling | C10: DOE Tribal Energy Financing Program (TEFP, formerly TELGP) can support UP TO 80% of eligible project costs (statutory ceiling, per DOE TEFP FAQ). Actual coverage depends on project cash flow capacity. TEFP is now administered by the DOE Office of Energy Dominance Financing (EDF), not the Loan Programs Office. The Working Families Tax Cut eliminated the prior Federal Support Restriction, allowing more permissive stacking with other federal incentives (including ITC + Direct Pay).
B11: DOE-IE grant updates | C11: Current grant cycle is the $50M 'Unleashing Tribal Energy Development' NOFO (DE-FOA-0003548), released March 25, 2026. Deadline: July 24, 2026 at 5:00 PM ET. TA1 (construction): up to $7.5M, 10% cost share. TA2 (community pre-development): up to $1.5M, 0% cost share. TA3 (large-scale planning, most relevant for nuclear): up to $2.5M, 0% cost share. Nuclear is explicitly listed as an eligible technology category.
B12: OBBBA phasedown for nuclear | C12: Nuclear ITC/PTC retains 100% credit value through 2033, then phases down: 75% in 2034, 50% in 2035, 0% in 2036+. This is more generous than the wind/solar phasedown (which begins immediately for wind/solar projects beginning construction after July 4, 2026). Source: P.L. 119-21 (OBBBA, July 4, 2025); Morgan Lewis, July 2025.
B13: FEOC restrictions | C13: Foreign Entity of Concern (FEOC) restrictions apply to projects beginning construction in 2026+. Specified Foreign Entities (SFE — entities tied to China, Russia, North Korea, Iran) are ineligible for §48E ITC and §45Y PTC. 'Material assistance' from SFE/FIE-sourced components above year-specific thresholds also disqualifies. Tribal projects need supply chain due diligence as a financing-close condition. Source: P.L. 119-21 (OBBBA); Morgan Lewis 2025.
B14: Non-electric end uses | C14: Beyond grid electricity, Tribal nuclear projects can deliver value via process heat, hydrogen, desalination, district heating, and data center co-location. Note: §45V clean hydrogen credit is REPEALED for projects beginning construction after Dec 31, 2025 under OBBBA, narrowing the timing window for nuclear-hydrogen pairing tax incentives.

Sheet Sources
B2: Source Citations
B4: Source | C4: URL
B5: DOE 'Unleashing Tribal Energy Development' $50M NOFO Announcement (March 2026) | C5: https://www.energy.gov/articles/energy-department-announces-50-million-investment-advance-affordable-reliable-and-secure
B6: DOE Office of Energy Dominance Financing (EDF) | C6: https://www.energy.gov/EDF
B7: DOE TEFP Frequently Asked Questions (80% cap, eligibility) | C7: https://www.energy.gov/edf/tribal-energy-financing-program-frequently-asked-questions
B8: DOE Tribal Energy Financing Program Page | C8: https://www.energy.gov/LPO/Tribal
B9: DOE/NETL Energy Community Mapping Tool | C9: https://arcgis.netl.doe.gov/portal/apps/experiencebuilder/experience/?id=785ee47a99d24b36b405acd03d97a5f9
B10: Wilson Center — Nuclear Power is Tribal Power | C10: https://www.wilsoncenter.org/article/nuclear-power-tribal-power
B11: Crux Climate — Transferable Tax Credits Market Pricing | C11: https://www.cruxclimate.com/insights/transferable-tax-credits
B12: Morgan Lewis — Domestic Content Bonus Adder Mechanics (PTC vs ITC) | C12: https://www.morganlewis.com/pubs/2023/05/irs-releases-highly-anticipated-guidance-on-domestic-content-ira-tax-credit-adder
B13: Plante Moran — PWA Requirements & <1MW Exemption | C13: https://www.plantemoran.com/explore-our-thinking/insight/2025/01/prevailing-wage-requirements-for-bonus-ira-energy-tax-credits
B14: U.S. Treasury — Press Release JY1830 (Tax Incentives Fact Sheet) | C14: https://home.treasury.gov/news/press-releases/jy1830
B15: U.S. Treasury — Press Release JY2775 (§48E(h) Final Rules, Jan 2025) | C15: https://home.treasury.gov/news/press-releases/jy2775
... B60: USET — Tribal Leader Letter on §48E(h) Guidance (Aug 2024) | C60: https://www.usetinc.org/wp-content/uploads/2024/09/DTLL_Guidance_on_Technology_Neutral_Low-Income_Communities_Bonus_Amoung_Program.pdf
